onepassword/__init__.py
onepassword/client.py
onepassword/exceptions.py
onepassword/utils.py
onepassword/version.py
1password-0.1.0.dist-info/LICENSE
1password-0.1.0.dist-info/METADATA
1password-0.1.0.dist-info/WHEEL
1password-0.1.0.dist-info/top_level.txt
1password-0.1.0.dist-info/RECORD
