Metadata-Version: 2.1
Name: 1password
Version: 0.1.0
Summary: A Python client and wrapper around the 1Password CLI.
Home-page: https://github.com/wandera/1password-client
Author: David Pryce
Author-email: david.pryce@wandera.com
License: MIT
Platform: UNKNOWN
Classifier: Programming Language :: Python :: 3
Classifier: License :: OSI Approved :: MIT License
Classifier: Operating System :: MacOS :: MacOS X
Requires-Python: >=3.7
Requires-Dist: wget (>=3.2)
Requires-Dist: pyyaml (>=5.1.2)
Requires-Dist: bs4 (>=0.0.1)
Requires-Dist: pycryptodome (>=3.9.7)
